runkeeper/Account.py
runkeeper/User.py
runkeeper/__init__.py
runkeeper-0.1.2.dist-info/LICENSE
runkeeper-0.1.2.dist-info/METADATA
runkeeper-0.1.2.dist-info/WHEEL
runkeeper-0.1.2.dist-info/top_level.txt
runkeeper-0.1.2.dist-info/RECORD
