Metadata-Version: 2.1
Name: runkeeper
Version: 0.1.2
Summary: Unofficial Python API Client for Runkeeper
Home-page: https://github.com/kajchang/runkeeper
Author: Kai Chang
License: MIT
Platform: UNKNOWN
Requires-Dist: requests (>=2.21.0)
